utils.py
xsprofile-0.0.8.dist-info/.ipynb_checkpoints/PKG-INFO-checkpoint
xsprofile-0.0.8.dist-info/.ipynb_checkpoints/SOURCES-checkpoint.txt
xsprofile-0.0.8.dist-info/.ipynb_checkpoints/dependency_links-checkpoint.txt
xsprofile-0.0.8.dist-info/.ipynb_checkpoints/requires-checkpoint.txt
xsprofile-0.0.8.dist-info/LICENSE.md
xsprofile-0.0.8.dist-info/METADATA
xsprofile-0.0.8.dist-info/WHEEL
xsprofile-0.0.8.dist-info/top_level.txt
xsprofile-0.0.8.dist-info/RECORD
