Metadata-Version: 2.1
Name: xsprofile
Version: 0.0.8
Summary: UNKNOWN
Home-page: https://gitlab.com/Geomorph/xsprofile
Author: Will Conley
Author-email: EcoRioGeo@gmail.com
License: UNKNOWN
Platform: UNKNOWN
Classifier: Programming Language :: Python :: 3
Classifier: Programming Language :: Python :: 3.9
Classifier: License :: OSI Approved :: GNU General Public License v2 (GPLv2)
Classifier: Operating System :: Microsoft :: Windows :: Windows 10
Requires-Python: >=3.9
License-File: LICENSE.md
Requires-Dist: geopandas
Requires-Dist: rasterio
Requires-Dist: matplotlib
